{
  "issues": [
    {
      "id": "hs_-8096431131862359684",
      "type": "high_coupling",
      "severity": "low",
      "message": "Component has high coupling degree of 2 (In: 0, Out: 2)",
      "affected_files": [
        "hello.py"
      ],
      "metadata": {}
    },
    {
      "id": "hs_4755069372207776394",
      "type": "high_coupling",
      "severity": "low",
      "message": "Component has high coupling degree of 2 (In: 1, Out: 1)",
      "affected_files": [
        "hello.py"
      ],
      "metadata": {}
    },
    {
      "id": "hs_6522048550320619904",
      "type": "high_coupling",
      "severity": "low",
      "message": "Component has high coupling degree of 2 (In: 2, Out: 0)",
      "affected_files": [
        "hello.py"
      ],
      "metadata": {}
    }
  ]
}